{
	"fixups":
	{
		"str_replace":
		[
			"|de.945radiocottbus|(Radio Cottbus)||",
			"|de.955charivari|***Neu***||",
			"|de.adultradio|- German Top 100 Single Charts -|-|",
			"|de.alternativefm|AlternativeFM - rockt. -||",
			"|de.antennelandau|(94.8 Antenne Landau)||",
			"|de.antennezweibruecken|(Antenne Zweibrücken 91.6)||",
			"|de.antennekids|Fernseh-Hit - ||",
			"|de.bayernplus|: | - |",
			"|de.campusfm|- (Testbetrieb)||",
			"|de.cityradiotrier|(Cityradio Trier 88.4)||",
			"|de.clubstars|Now On Air:||",
			"|de.cremfm|songs - ||",
			"|de.clublovers|Clublovers.FM - ||",
			"|de.dasding| /// | - |",
			"|de.dieneuewelle|die neue welle - Der beste Musikmix aus 4 Jahrzehnten! - ||",
			"|de.dierockwelle|AlternativeFM - rockt. - ||",
			"!de.fun80s!Einfach Deutsch | !!",
			"!de.germany-stream!| Germany Stream Berlin!!",
			"|de.ichtysradio|***Wunschbox On-Air*** ||",
			"|de.isimsizfm|(128 kb/s MP3 Stream)||",
			"|de.jumpinthemix|im MDR JUMP In The Mix Channel ||",
			"|de.jumppiraten|im MDR JUMP In The Mix Channel ||",
			"|de.jumprock|im MDR JUMP Rock Channel ||",
			"|de.jumptrend|im MDR JUMP Trend Channel ||",
			"|de.radioidaroberstein|(87.6 Radio Idar-Oberstein)||",
			"|de.radiomerzig|(Radio Merzig)||",
			"|de.radioneunkirchen|(Radio Neunkirchen)||",
			"|de.radioffo|(Radio Frankfurt 99.3)||",
			"!de.radiosaw80er!| radio SAW-80er!!",
			"!de.radiosaw90er!| radio SAW-90er!!",
			"|de.romantic|(Romantic Radio ... Dein Kuschelsender auf www.hello-city.de)||",
			"|de.schwarzewelle|(onAir: Schwarze Welle)||",
			"!de.sunshine-live!| radio sunshine live :: electronic music web!!",
			"|de.swr1|Sie hoeren: ||",
			"|de.swr1bw|Sie hoeren: ||",
			"|de.swr1rp|Sie hoeren: ||",
			"|de.swr4|Sie hoeren: ||",
			"|de.swr4bw|Sie hoeren: ||",
			"|de.swr4rp|Sie hoeren: ||",
			"|de.tanzfm|On Air: ||",
			
			""
		],
	
		"preg_replace":
		[
			"|de.autoscooter|^[0-9]* - |||",
			"|de.campusfm|^\\([0-9:]*\\) |||",
			"|de.palmenstrandradio|\\.\\.::.*?::\\.\\.|||",
			"|de.dasding|^\\/\\/\\/ |||",
			"|de.trance-nation|\\* \\( \\(¯`»\\. \\.«[^»]*»\\. \\.«´¯\\)\\)\\*|||",
			
			""
		]
	},

	"nuke":
	{
		"strstr":
		[
			"|de.007fm|No Artist - |",
			"|de.1055spreeradio|Die Besten Songs Aller Zeiten|",
			"|de.1live|1LIVE|",
			"|de.1live|1livediggi.de|",
			"|de.890rtl|89.0 Rtl|",
			"|de.890rtl|89.0rtl|",
			"|de.1046rtl|Www.104.6rtl.Com|",
			"|de.945radiocottbus|Werbung|",
			"|de.955charivari|Radio Charivari|",
			"|de.antenne80er|ANTENNE BAYERN|",
			"|de.antennebayern|ANTENNE BAYERN|",
			"|de.antennemainz|Werbung|",
			"|de.antennealternative|ROCK ANTENNE|",
			"|de.antenneclassicrock|ANTENNE BAYERN|",
			"|de.antenneheavy|ROCK ANTENNE|",
			"|de.antennemv|Antenne MV|",
			"|de.antenneoldies|ANTENNE BAYERN|",
			"|de.antennetop40|ANTENNE BAYERN|",
			"|de.altstadtwelle|LIVE aus dem Studio|",
			"|de.bayern1|Bayern 1|",
			"|de.bayern1|bayern1.de|",
			"|de.bayern1|Titel: |",
			"|de.bayern1|Interpret: |",
			"|de.bayern1|Kostenloses |",
			"|de.bayern2|Bayern 2|",
			"|de.bayern2|bayern2.de|",
			"|de.bayern2|+++ |",
			"|de.bayern2|radioWelt: |",
			"|de.bayern2|kulturWelt|",
			"|de.bayern3|Bayern 3|",
			"|de.bayern3|BAYERN 3|",
			"|de.bayern3|bayern3.de|",
			"|de.bayern3|Studio-Hotline:|",
			"|de.bayernplus|Servus Bayern|",
			"|de.bayernplus|Bayern plus|",
			"|de.bayernplus|BAYERN plus|",
			"|de.bayernplus|Heute ist|",
			"|de.campusfm|www.campusfm.info|",
			"|de.chartsradio|dropin|",
			"|de.cremfm|!WERBUNG!|",
			"|de.cremfm|!Werbung!|",
			"|de.cremfm|!Jingle!|",
			"|de.crosschannel|www.CrossChannel.de|",
			"|de.dasbremerpartyradio|live on Air|",
			"|de.dasbremerpartyradio|Live on Air|",
			"|de.deltaradio|delta radio - |",
			"|de.deutschlandfunk|Nachrichten|",
			"|de.deutschradio|Jingle-Deutschradio|",
			"|de.dierockwelle|deine Nachrichten|",
			"|de.dublovers|dropin|",
			"|de.ebmradio|( ( (|",
			"|de.erfpop|ERF Pop|",
			"|de.ffncomedy|ffn comedy - |",
			"|de.funkhauseuropa|Funkhaus Europa|",
			"|de.funkhauseuropa|Sie hoeren - |",
			"|de.funkhauseuropa|eMail:|",
			"|de.funkhauseuropa|www.funkhauseuropa.de|",
			"|de.funkhauseuropa|Hotline -|",
			"|de.hellwegradio|www.hellwegradio.de|",
			"|de.hitstationfmschlager|Hitstation.fm -|",
			"|de.hochschulradioa|On Air >>>|",
			"|de.irabo|Irabo - |",
			"|de.peppermint|ffn Peppermint - |",
			"|de.radioarabella|Radio Arabella Deutschland|",
			"|de.radioaugsburg|Radio Augsburg -|",
			"|de.radionora|Radio NORA - |",
			"|de.sunshine-live|radio sunshine live ::|",
			"|de.swr1|Swr 1|",
			"|de.swr1|SWR1|",
			"|de.swr1|S W R 1|",
			"|de.swr1|SWR 1|",
			"|de.swr1|Moderation:|",
			"|de.swr1bw|Swr 1|",
			"|de.swr1bw|SWR1|",
			"|de.swr1bw|S W R 1|",
			"|de.swr1bw|SWR 1|",
			"|de.swr1bw|Moderation:|",
			"|de.swr1rp|Swr 1|",
			"|de.swr1rp|SWR1|",
			"|de.swr1rp|S W R 1|",
			"|de.swr1rp|SWR 1|",
			"|de.swr1rp|Moderation:|",
			"|de.swr3|Swr3|",
			"|de.swr3|SWR3|",
			"|de.swr3|Am Mikrofon: |",
			"|de.swr4|Swr4|",
			"|de.swr4|SWR4|",
			"|de.swr4|S W R 4|",
			"|de.swr4|Verkehrsnachrichten|",
			"|de.swr4bw|Swr4|",
			"|de.swr4bw|SWR4|",
			"|de.swr4bw|S W R 4|",
			"|de.swr4bw|Verkehrsnachrichten|",
			"|de.swr4rp|Swr4|",
			"|de.swr4rp|SWR4|",
			"|de.swr4rp|S W R 4|",
			"|de.swr4rp|Verkehrsnachrichten|",
			"|de.wdr2|WDR 2|",
			"|de.wdr2|www.wdr2.de|",
			"|de.wdr2aachen|WDR 2|",
			"|de.wdr2aachen|www.wdr2.de|",
			"|de.wdr2bergisches|WDR 2|",
			"|de.wdr2bergisches|www.wdr2.de|",
			"|de.wdr2muensterland|WDR 2|",
			"|de.wdr2muensterland|www.wdr2.de|",
			"|de.wdr2ostwestfalen|WDR 2|",
			"|de.wdr2ostwestfalen|www.wdr2.de|",
			"|de.wdr2rheinland|WDR 2|",
			"|de.wdr2rheinland|www.wdr2.de|",
			"|de.wdr2rheinruhr|WDR 2|",
			"|de.wdr2rheinruhr|www.wdr2.de|",
			"|de.wdr2ruhrgebiet|WDR 2|",
			"|de.wdr2ruhrgebiet|www.wdr2.de|",
			"|de.wdr2suedwestfalen|WDR 2|",
			"|de.wdr2suedwestfalen|www.wdr2.de|",
			
			""
		],
	
		"preg_match":
		[
			"|de.antenneblackbeatz|^-$||",
			"|de.big-up|^Ad$||",
			"|de.bigmusicblack|^[0-9a-z]*$||",
			"|de.bigmusicrnb|^[0-9a-z]*$||",
			"|de.bigmusicrock|^[0-9a-z]*$||",
			"|de.crm924|^Ad$|",
			"|de.dasding| \\/\\/\\/$||",
			"|de.dieneuewelle|^Aktuell$||",
			"|de.germanyradio|^news |",
			
			""
		]
	},
	
	"reverse":
	[
		"de.swr3",
		"de.swr4",
		
		""
	],
	
	"ignore":
	[
		"de.0098",
		"de.1-radio-latino",
		"de.anmradio",
		"de.antennesylt",
		"de.b5aktuell",
		"de.b5plus",
		"de.bashfm",
		"de.basslover",
		"de.bassloverclub",
		"de.bayerwaldradio",
		"de.bigrussia",
		"de.bollywoodradio",
		"de.bunkertv",
		"de.brklassik",
		"de.chromanovaambient",
		"de.chromanovapsy",
		"de.classical102",
		"de.clubtunesfm",
		"de.cosmicmusic",
		"de.damarfm",
		"de.deutschlandfunk",
		"de.dieneuewelle",
		"de.divbyzeroambient",
		"de.divbyzerooldschool",
		"de.divbyzeroprogressive",
		"de.divbyzerotrance",
		"de.dradiowissen",
		"de.dkultur",
		"de.elektrosounds",
		"de.erf",
		"de.fashionradio",
		"de.goatranceradio",
		"de.hardlovers",
		"de.klassiklounge",
		"de.klassikmovie",
		"de.klassikradio",
		"de.klassikradiomovie",
		"de.isimsizfm",
		"de.lobpreis",
		"de.lukesspielwiese",
		"de.njoyflavormix",
		"de.radioaena",
		"de.schwany1",
		"de.schwany3",
		"de.schwany4",
		"de.schwany5",
		"de.swr2",
		"de.swrinfo",
		"de.tierstimmen",
		"de.wdr3",
		"de.wdr4",
		"de.wdr5",
		"de.wdrevent",
		
		""
	]
}
